{
    "free_games": [
        {
            "id": "the_sims_4_my_first_pet_stuff",
            "game_name": "The Sims\u2122 4 My First Pet Stuff",
            "game_url": "https://store.epicgames.com/en-US/p/the-sims-4--my-first-pet-stuff",
            "start_date": "2023-12-01T11:00:00+00:00",
            "end_date": "2024-01-09T18:00:00+00:00",
            "image_link": "https://thelovinator1.github.io/discord-free-game-notifier/images/ac_syndicate.png",
            "description": "Welcome home a new small animal and show love for Cats and Dogs with The Sims\u2122 4 My First Pet Stuff.\n\n[Instant Checkout](https://store.epicgames.com/purchase?offers=1-2a14cf8a83b149919a2399504e5686a6-7002cdb1eb2543da85ac8a3c4c6d71d5#/)",
            "developer": "Maxis"
        }
    ]
}